lintmon/__init__.py
lintmon/config.py
lintmon/lintmon.py
lintmon/monitor_session.py
lintmon/settings.py
lintmon/utils.py
lintmon-0.2.0.dist-info/entry_points.txt
lintmon-0.2.0.dist-info/LICENSE
lintmon-0.2.0.dist-info/WHEEL
lintmon-0.2.0.dist-info/METADATA
lintmon-0.2.0.dist-info/RECORD
