Metadata-Version: 2.1
Name: lintmon
Version: 0.2.0
Summary: Monitor project files in the background for lint issues and flag issues in your prompt
Home-page: https://github.com/daphtdazz/lintmon
License: Apache-2.0
Author: David Park
Author-email: david@greenparksoftware.co.uk
Requires-Python: >=3.8
Classifier: License :: OSI Approved :: Apache Software License
Classifier: Operating System :: OS Independent
Classifier: Programming Language :: Python :: 3
Classifier: Programming Language :: Python :: 3.10
Classifier: Programming Language :: Python :: 3.8
Classifier: Programming Language :: Python :: 3.9
Requires-Dist: PyYAML (>=6.0)
Requires-Dist: psutil (>=5.8.0)
Project-URL: Repository, https://github.com/daphtdazz/lintmon
